[{"variable":"o_econ_impact_how_long_months","value":"1","total":9,"perc_of_total":0.0437,"label_ne":"६ महिना भन्दा कम","label_en":"Less than 6 months"},{"variable":"o_econ_impact_how_long_months","value":"2","total":74,"perc_of_total":0.3592,"label_ne":"६ देखि १२ महिना सम्म","label_en":"6 to 12 months"},{"variable":"o_econ_impact_how_long_months","value":"3","total":68,"perc_of_total":0.3301,"label_ne":"१३ देखि २४ महिना सम्म","label_en":"13 to 24 months"},{"variable":"o_econ_impact_how_long_months","value":"4","total":55,"perc_of_total":0.267,"label_ne":"२४ महिना भन्दा बढी","label_en":"24 months or more"}]
